nuspacesim/compute.py
nuspacesim/__main__.py
nuspacesim/state.py
nuspacesim/_version.py
nuspacesim/results_table.py
nuspacesim/constants.py
nuspacesim/__init__.py
nuspacesim/config.py
nuspacesim/apps/create_config.py
nuspacesim/apps/__main__.py
nuspacesim/apps/cli.py
nuspacesim/apps/utils.py
nuspacesim/apps/show_plot.py
nuspacesim/apps/run.py
nuspacesim/apps/__init__.py
nuspacesim/data/compare_nupyprop_tables.py
nuspacesim/data/make_nu2tau.py
nuspacesim/data/concatenate_nupyprop_tables.py
nuspacesim/data/__init__.py
nuspacesim/data/CONEX_table/dumpGH_conex_pi_E17_95deg_0km_eposlhc_1394249052_211.dat
nuspacesim/data/CONEX_table/__init__.py
nuspacesim/data/RenoNu2TauTables/read_reno_nu2tautables.py
nuspacesim/data/RenoNu2TauTables/__init__.py
nuspacesim/data/nupyprop_tables/nu2tau_cdf.2.h5
nuspacesim/data/nupyprop_tables/nu2tau_pexit.3.h5
nuspacesim/data/nupyprop_tables/nu2tau_cdf.1.h5
nuspacesim/data/nupyprop_tables/nu2tau_pexit.2.h5
nuspacesim/data/nupyprop_tables/nu2tau_pexit.1.h5
nuspacesim/data/nupyprop_tables/nu2tau_cdf.3.h5
nuspacesim/data/nupyprop_tables/__init__.py
nuspacesim/data/nuleptonsim_tables/nu2tau_pexit.0.h5
nuspacesim/data/nuleptonsim_tables/nu2tau_cdf.0.h5
nuspacesim/data/nuleptonsim_tables/__init__.py
nuspacesim/data/radio_params/ionosphere_params.hdf5
nuspacesim/data/radio_params/waveform_params.hdf5
nuspacesim/data/radio_params/__init__.py
nuspacesim/data/cloud_maps/nss_map_CloudTopPressure_12.v0.fits
nuspacesim/data/cloud_maps/nss_map_CloudTopPressure_05.v0.fits
nuspacesim/data/cloud_maps/nss_map_CloudTopPressure_03.v0.fits
nuspacesim/data/cloud_maps/nss_map_CloudTopPressure_02.v0.fits
nuspacesim/data/cloud_maps/nss_map_CloudTopPressure_11.v0.fits
nuspacesim/data/cloud_maps/nss_map_CloudTopPressure_09.v0.fits
nuspacesim/data/cloud_maps/nss_map_CloudTopPressure_01.v0.fits
nuspacesim/data/cloud_maps/nss_map_CloudTopPressure_06.v0.fits
nuspacesim/data/cloud_maps/nss_map_CloudTopPressure_08.v0.fits
nuspacesim-2.1.0.dist-info/RECORD
nuspacesim-2.1.0.dist-info/METADATA
nuspacesim-2.1.0.dist-info/entry_points.txt
nuspacesim-2.1.0.dist-info/top_level.txt
nuspacesim-2.1.0.dist-info/WHEEL
nuspacesim-2.1.0.dist-info/licenses/LICENSE.txt
