Metadata-Version: 2.4
Name: nuspacesim
Version: 2.1.0
Summary: A Simulator for Space-based Neutrino Detections
Author: Alex Reustle
Author-email: alexander.reustle@nasa.gov
License: BSD-3-Clause-Clear
Keywords: NASA,neutrinos,Simulation
Classifier: Intended Audience :: Science/Research
Classifier: License :: OSI Approved :: BSD License
Classifier: Programming Language :: C++
Classifier: Programming Language :: Python :: 3
Classifier: Programming Language :: Python :: 3 :: Only
Classifier: Programming Language :: Python :: 3.9
Classifier: Programming Language :: Python :: 3.10
Classifier: Programming Language :: Python :: 3.11
Classifier: Programming Language :: Python :: 3.12
Classifier: Programming Language :: Python :: 3.13
Requires-Python: >=3.9
License-File: LICENSE.txt
Requires-Dist: astropy>=4.3
Requires-Dist: click>=8.0.3
Requires-Dist: cubepy
Requires-Dist: dask
Requires-Dist: dask[distributed]
Requires-Dist: h5py
Requires-Dist: matplotlib
Requires-Dist: numpy>=1.21
Requires-Dist: pydantic
Requires-Dist: rich
Requires-Dist: scipy
Requires-Dist: tomli-w
Requires-Dist: configparser; python_version < "3.8"
Requires-Dist: importlib-metadata; python_version < "3.8"
Requires-Dist: importlib-resources; python_version < "3.9"
Requires-Dist: tomli; python_version < "3.11"
Dynamic: license-file
